sitri/__init__.py
sitri/configurator.py
sitri/logger.py
sitri/providers/__init__.py
sitri/providers/base/__init__.py
sitri/providers/base/base_config_path_mode.py
sitri/providers/base/base_config_provider.py
sitri/providers/contrib/__init__.py
sitri/providers/contrib/ini.py
sitri/providers/contrib/json.py
sitri/providers/contrib/redis.py
sitri/providers/contrib/system.py
sitri/providers/contrib/toml.py
sitri/providers/contrib/vault/__init__.py
sitri/providers/contrib/vault/vault_kv.py
sitri/providers/contrib/vedis.py
sitri/providers/contrib/yaml.py
sitri/settings/__init__.py
sitri/settings/base.py
sitri/settings/contrib/__init__.py
sitri/settings/contrib/vault/__init__.py
sitri/settings/contrib/vault/vault_kv.py
sitri/settings/contrib/yaml.py
sitri/strategy/__init__.py
sitri/strategy/base.py
sitri/strategy/index_priority.py
sitri/strategy/single.py
sitri-2.2.12.dist-info/WHEEL
sitri-2.2.12.dist-info/METADATA
sitri-2.2.12.dist-info/licenses/LICENSE
sitri-2.2.12.dist-info/RECORD
