Metadata-Version: 2.1
Name: sitri
Version: 2.2.12
Summary: Library for one endpoint config managment
License: MIT
Keywords: packaging,poetry,config,configuration,managment,vault,pydantic,json,yaml,environment
Author-email: Alexander Lavrov <admin@egnod.dev>
Requires-Python: >=3.7,<3.12
Classifier: Development Status :: 5 - Production/Stable
Classifier: Environment :: Other Environment
Classifier: Intended Audience :: Developers
Classifier: Intended Audience :: Science/Research
Classifier: License :: OSI Approved :: MIT License
Classifier: Operating System :: OS Independent
Classifier: Programming Language :: Python
Classifier: Topic :: Software Development :: Libraries :: Python Modules
Provides-Extra: all
Requires-Dist: redis>=4.3.4; extra == "all"
Requires-Dist: vedis>=0.7.1; extra == "all"
Requires-Dist: pyyaml>=6.0; extra == "all"
Requires-Dist: hvac>=0.11.2; extra == "all"
Requires-Dist: pydantic>=1.9.1; extra == "all"
Requires-Dist: orjson>=3.8.1; extra == "all"
Requires-Dist: tomli>=2.0.1; extra == "all"
Requires-Dist: tomli-w>=1.0.0; extra == "all"
Provides-Extra: hvac
Requires-Dist: hvac>=0.11.2; extra == "hvac"
Provides-Extra: orjson
Requires-Dist: orjson>=3.8.1; extra == "orjson"
Provides-Extra: pyyaml
Requires-Dist: pyyaml>=6.0; extra == "pyyaml"
Provides-Extra: redis
Requires-Dist: redis>=4.3.4; extra == "redis"
Provides-Extra: settings
Requires-Dist: pydantic>=1.9.1; extra == "settings"
Provides-Extra: toml
Requires-Dist: tomli>=2.0.1; extra == "toml"
Requires-Dist: tomli-w>=1.0.0; extra == "toml"
Provides-Extra: vedis
Requires-Dist: vedis>=0.7.1; extra == "vedis"
Project-URL: documentation, https://sitri.readthedocs.io
Project-URL: repository, https://github.com/Egnod/sitri
